<sequential display_name="Lecture 5: SaaS Architecture and Introduction to Rails">
  <vertical url_name="vertical_b6dfccf39862"/>
  <vertical url_name="vertical_72714b255c63"/>
  <vertical url_name="vertical_7e1355432af6"/>
  <vertical url_name="vertical_688ca7f1d229"/>
  <vertical url_name="vertical_2190f9d5c631"/>
  <vertical url_name="vertical_fd032ca2d433"/>
  <vertical url_name="vertical_d1a5899b8a9c"/>
  <vertical url_name="vertical_5e743489d4cd"/>
  <vertical url_name="vertical_f7c0e87fd6bd"/>
  <vertical url_name="vertical_885203f8fb53"/>
  <vertical url_name="vertical_4b98908fc524"/>
  <vertical url_name="vertical_de057f6f5bf1"/>
</sequential>
