<problem attempts="1" display_name="quiz 2-14">
  <text>
  Which of the following are true about user stories? Select all that apply.
</text>
  <choiceresponse>
    <checkboxgroup>
      <choice correct="true">
        <text>They should describe how the application is expected to be used</text>
      </choice>
      <choice correct="true">
        <text>They should have business value</text>
      </choice>
      <choice correct="false">
        <text>They do not need to be testable</text>
      </choice>
      <choice correct="false">
        <text>They should be implemented across multiple iterations of the Agile lifecycle</text>
      </choice>
    </checkboxgroup>
  </choiceresponse>
</problem>
